{"client":"Thunder Client","collectionName":"sudoku solver requests","dateExported":"2021-06-07T07:10:55.487Z","version":"1.1","folders":[],"requests":[{"containerId":"","sortNum":10000,"headers":[{"name":"Authorization_1","value":"cDb4F9118b1F1d33227115F09f97BB7a"},{"name":"Authorization_2","value":"B034B7fDB805840a96df524C6E007bc2"}],"colId":"8b2b538d-e643-4c07-8fe9-9c7c8df85b61","name":"sudoku solver hill climbing example request","url":"http://localhost:3000/hill_climbing","method":"GET","modified":"2021-06-07T07:10:46.355Z","created":"2021-05-30T02:56:03.476Z","_id":"559107b2-b69e-4462-8785-00363a9da3b0","body":{"type":"json","raw":"{\n  \"board_array\": [\n    [0, 3, 0, 4],\n    [4, 0, 3, 2],\n    [1, 0, 0, 0],\n    [0, 0, 2, 1]\n  ],\n  \"zone_length\": 2,\n  \"zone_height\": 2,\n  \"restarts\": 2,\n  \"searchs\": 100\n}"},"tests":[]},{"containerId":"","sortNum":20000,"headers":[{"name":"Authorization_1","value":"cDb4F9118b1F1d33227115F09f97BB7a"},{"name":"Authorization_2","value":"B034B7fDB805840a96df524C6E007bc2"}],"colId":"8b2b538d-e643-4c07-8fe9-9c7c8df85b61","name":"sudoku solver genetic algorithm example request","url":"http://localhost:3000/genetic_algorithm","method":"GET","modified":"2021-06-07T07:10:38.576Z","created":"2021-06-04T21:25:07.539Z","_id":"5fa7c88b-79f7-469a-aa02-cc517ff1cefc","body":{"type":"json","raw":"{\n  \"board_array\": [\n    [0, 3, 0, 4],\n    [4, 0, 3, 2],\n    [1, 0, 0, 0],\n    [0, 0, 2, 1]\n  ],\n  \"zone_length\": 2,\n  \"zone_height\": 2,\n  \"restarts\": 2,\n  \"searchs\": 100\n}"},"tests":[]}]}
